latesteartquake/__init__.py
idn_quake_info-0.1.1.dist-info/LICENSE
idn_quake_info-0.1.1.dist-info/METADATA
idn_quake_info-0.1.1.dist-info/WHEEL
idn_quake_info-0.1.1.dist-info/top_level.txt
idn_quake_info-0.1.1.dist-info/RECORD
